mail_editor/__init__.py
mail_editor/admin.py
mail_editor/forms.py
mail_editor/helpers.py
mail_editor/mail_template.py
mail_editor/models.py
mail_editor/process.py
mail_editor/settings.py
mail_editor/urls.py
mail_editor/utils.py
mail_editor/views.py
mail_editor/management/__init__.py
mail_editor/management/commands/__init__.py
mail_editor/management/commands/add_missing_templates.py
mail_editor/migrations/0001_initial.py
mail_editor/migrations/0002_auto_20170227_1438.py
mail_editor/migrations/0003_delete_mail.py
mail_editor/migrations/0004_auto_20170406_1814.py
mail_editor/migrations/0005_auto_20200220_1656.py
mail_editor/migrations/0006_mailtemplate_base_template_path.py
mail_editor/migrations/0007_auto_20200415_1513.py
mail_editor/migrations/0008_auto_20200416_1055.py
mail_editor/migrations/0009_auto_20200416_1105.py
mail_editor/migrations/0010_auto_20210422_1354.py
mail_editor/migrations/0011_alter_mailtemplate_unique_together.py
mail_editor/migrations/0012_auto_20230102_1549.py
mail_editor/migrations/0013_alter_mailtemplate_language.py
mail_editor/migrations/__init__.py
mail_editor/templates/admin/mail_editor/change_form.html
mail_editor/templates/admin/mail_editor/preview_form.html
mail_editor/templates/mail/_base.html
mail_editor/templates/mail/_outer_table.html
mail_editor-0.3.8.dist-info/licenses/LICENSE
mail_editor-0.3.8.dist-info/METADATA
mail_editor-0.3.8.dist-info/WHEEL
mail_editor-0.3.8.dist-info/top_level.txt
mail_editor-0.3.8.dist-info/RECORD
