Metadata-Version: 2.4
Name: mail_editor
Version: 0.3.8
Summary: A Django package for email template editing
Author-email: Maykin Media <support@maykinmedia.nl>
License: Copyright (c) Maykin Media and individual contributors.
Project-URL: Homepage, https://github.com/maykinmedia/mail-editor
Project-URL: Documentation, https://github.com/maykinmedia/mail-editor
Project-URL: Bug Tracker, https://github.com/maykinmedia/mail-editor/issues
Project-URL: Source Code, https://github.com/maykinmedia/mail-editor
Keywords: TODO
Classifier: Development Status :: 3 - Alpha
Classifier: Environment :: Web Environment
Classifier: Framework :: Django
Classifier: Framework :: Django :: 3.2
Classifier: Framework :: Django :: 4.2
Classifier: Intended Audience :: Developers
Classifier: License :: OSI Approved :: BSD License
Classifier: Operating System :: Unix
Classifier: Operating System :: MacOS
Classifier: Operating System :: Microsoft :: Windows
Classifier: Programming Language :: Python
Classifier: Programming Language :: Python :: 3.10
Classifier: Programming Language :: Python :: 3.11
Classifier: Programming Language :: Python :: 3.12
Classifier: Topic :: Internet :: WWW/HTTP
Classifier: Topic :: Internet :: WWW/HTTP :: Dynamic Content
Classifier: Topic :: Software Development :: Libraries :: Python Modules
Requires-Python: >=3.10
License-File: LICENSE
Requires-Dist: django>=3.2
Requires-Dist: django-choices
Requires-Dist: django-ckeditor
Requires-Dist: requests
Requires-Dist: lxml
Requires-Dist: css_inline
Provides-Extra: tests
Requires-Dist: pytest; extra == "tests"
Requires-Dist: pytest-django; extra == "tests"
Requires-Dist: tox; extra == "tests"
Requires-Dist: isort; extra == "tests"
Requires-Dist: black; extra == "tests"
Requires-Dist: flake8; extra == "tests"
Requires-Dist: autoflake; extra == "tests"
Requires-Dist: django_webtest; extra == "tests"
Provides-Extra: coverage
Requires-Dist: pytest-cov; extra == "coverage"
Provides-Extra: release
Requires-Dist: bump-my-version; extra == "release"
Requires-Dist: twine; extra == "release"
Dynamic: license-file
